databridges_nacl_wrapper/__init__.py
databridges_nacl_wrapper/databridges_nacl_wrapper.py
databridges_nacl_wrapper-1.0.1.dist-info/LICENSE
databridges_nacl_wrapper-1.0.1.dist-info/WHEEL
databridges_nacl_wrapper-1.0.1.dist-info/METADATA
databridges_nacl_wrapper-1.0.1.dist-info/RECORD
