Metadata-Version: 2.1
Name: databridges_nacl_wrapper
Version: 1.0.1
Summary: DataBridges Python nacl wrapper for databridges library.
Keywords: optomate,databridges,pubsub,rpc,websocket,socket.io,ws,events,realtime,real-time,nacl,encryption
Author-email: "Optomate Technologies Private Limited." <tech@optomate.io>
Classifier: License :: OSI Approved :: MIT License
Requires-Dist: PyNaCl==1.5.0
Project-URL: Documentation, https://github.com/databridges-io/lib.python.nacl.wrapper
Project-URL: Source, https://github.com/databridges-io/lib.python.nacl.wrapper
